target_describe/__init__.py
target_describe/target_describe.py
target_describe/utils.py
target_describe-0.0.3.dist-info/LICENSE
target_describe-0.0.3.dist-info/METADATA
target_describe-0.0.3.dist-info/WHEEL
target_describe-0.0.3.dist-info/top_level.txt
target_describe-0.0.3.dist-info/RECORD
