Metadata-Version: 2.1
Name: target-describe
Version: 0.0.3
Summary: Generate viz for your variables with your target for ML
Home-page: https://github.com/DanielR59/target_description
Author: Daniel Rosas
Author-email: daniel_pumas_59@hotmail.com
License: MIT
Platform: UNKNOWN
Classifier: Programming Language :: Python :: 3
Classifier: Programming Language :: Python :: 3.7
Classifier: Programming Language :: Python :: 3.9
License-File: LICENSE
Requires-Dist: nbformat (==5.1.3)
Requires-Dist: numpy (>=1.20.0)
Requires-Dist: pandas (>=1.3.1)
Requires-Dist: plotly (==5.6.0)
Requires-Dist: tenacity (==8.0.1)
